lusid_scheduler/__init__.py
lusid_scheduler/api/__init__.py
lusid_scheduler/api/application_metadata_api.py
lusid_scheduler/api/images_api.py
lusid_scheduler/api/jobs_api.py
lusid_scheduler/api/schedules_api.py
lusid_scheduler/api_client.py
lusid_scheduler/api_response.py
lusid_scheduler/configuration.py
lusid_scheduler/exceptions.py
lusid_scheduler/extensions/__init__.py
lusid_scheduler/extensions/api_client.py
lusid_scheduler/extensions/api_client_factory.py
lusid_scheduler/extensions/api_configuration.py
lusid_scheduler/extensions/configuration_loaders.py
lusid_scheduler/extensions/configuration_options.py
lusid_scheduler/extensions/file_access_token.py
lusid_scheduler/extensions/proxy_config.py
lusid_scheduler/extensions/refreshing_token.py
lusid_scheduler/extensions/rest.py
lusid_scheduler/extensions/retry.py
lusid_scheduler/extensions/socket_keep_alive.py
lusid_scheduler/extensions/tcp_keep_alive_connector.py
lusid_scheduler/models/__init__.py
lusid_scheduler/models/access_controlled_action.py
lusid_scheduler/models/access_controlled_resource.py
lusid_scheduler/models/action_id.py
lusid_scheduler/models/argument_definition.py
lusid_scheduler/models/create_job_request.py
lusid_scheduler/models/create_schedule_request.py
lusid_scheduler/models/id_selector_definition.py
lusid_scheduler/models/identifier_part_schema.py
lusid_scheduler/models/image.py
lusid_scheduler/models/image_summary.py
lusid_scheduler/models/job_definition.py
lusid_scheduler/models/job_history.py
lusid_scheduler/models/job_run_result.py
lusid_scheduler/models/link.py
lusid_scheduler/models/lusid_problem_details.py
lusid_scheduler/models/lusid_validation_problem_details.py
lusid_scheduler/models/notification.py
lusid_scheduler/models/repository.py
lusid_scheduler/models/required_resources.py
lusid_scheduler/models/resource_id.py
lusid_scheduler/models/resource_list_of_access_controlled_resource.py
lusid_scheduler/models/resource_list_of_image_summary.py
lusid_scheduler_sdk-2.2.1.dist-info/METADATA
lusid_scheduler_sdk-2.2.1.dist-info/WHEEL
lusid_scheduler_sdk-2.2.1.dist-info/RECORD
